faker_starship/__init__.py
faker_starship/library/__init__.py
faker_starship/library/babylon5.py
faker_starship/library/battlestargalactica.py
faker_starship/library/blakes7.py
faker_starship/library/commonwealth.py
faker_starship/library/culture.py
faker_starship/library/darkmatter.py
faker_starship/library/eveonline.py
faker_starship/library/farscape.py
faker_starship/library/firefly.py
faker_starship/library/halo.py
faker_starship/library/imperialradch.py
faker_starship/library/lexx.py
faker_starship/library/reddwarf.py
faker_starship/library/startrek.py
faker_starship/library/starwars.py
faker_starship/library/theexpanse.py
faker_starship/library/theorville.py
faker_starship/library/travellerrpg.py
faker_starship/library/warhammer40k.py
faker_starship-0.0.1a1.dist-info/LICENSE
faker_starship-0.0.1a1.dist-info/METADATA
faker_starship-0.0.1a1.dist-info/WHEEL
faker_starship-0.0.1a1.dist-info/top_level.txt
faker_starship-0.0.1a1.dist-info/RECORD
