Metadata-Version: 2.1
Name: faker-starship
Version: 0.0.1a1
Summary: Provider of various starship data for the Faker Python package.
Home-page: https://gitlab.com/infinitewarp/faker-starship
Author: Brad Smith
Author-email: bradster@infinitewarp.com
License: MIT
Keywords: faker provider starship test data
Platform: UNKNOWN
Classifier: Development Status :: 3 - Alpha
Classifier: Intended Audience :: Developers
Classifier: License :: OSI Approved :: MIT License
Classifier: Operating System :: OS Independent
Classifier: Programming Language :: Python
Classifier: Programming Language :: Python :: 2
Classifier: Programming Language :: Python :: 2.7
Classifier: Programming Language :: Python :: 3
Classifier: Programming Language :: Python :: 3.6
Classifier: Programming Language :: Python :: 3.7
Classifier: Topic :: Software Development
Classifier: Topic :: Software Development :: Libraries
Classifier: Topic :: Software Development :: Libraries :: Python Modules
Requires-Dist: faker
